{
  "tools": {
    "cloudflare_get_zone_analytics": {
      "description": "Get zone analytics/stats for traffic, requests, and bandwidth.\n\n    Returns analytics data including requests, bandwidth, threats, and page views\n    for the specified time period.\n\n    Args:\n        params: GetZoneAnalyticsInput with zone and time range\n\n    Returns:\n        Analytics data with traffic statistics and metrics\n\n    Time range examples:\n        - Last 24 hours: since='-1440'\n        - Last 7 days: since='-10080'\n        - Specific range: since='2025-01-01T00:00:00Z', until='2025-01-07T00:00:00Z'\n    ",
      "maps_to": "cloudflare_get_zone_analytics",
      "server": "cloudflare-full",
      "inputSchema": {
        "properties": {
          "params": {
            "$ref": "#/$defs/GetZoneAnalyticsInput"
          }
        },
        "required": [
          "params"
        ],
        "type": "object"
      }
    }
  }
}
